ratify/__init__.py
ratify/ratify.py
tests/__init__.py
tests/test_ratify.py
ratify-0.4.0.dist-info/METADATA
ratify-0.4.0.dist-info/WHEEL
ratify-0.4.0.dist-info/top_level.txt
ratify-0.4.0.dist-info/RECORD
