Metadata-Version: 2.1
Name: ratify
Version: 0.4.0
Summary: A simple validation library
Home-page: https://github.com/Thobeats/ratify
Author: tobiy23@gmail.com
License: UNKNOWN
Project-URL: Documentation, https://iyanu.com.ng/ratify
Platform: UNKNOWN
Requires-Python: >=3.6
Requires-Dist: datetime
Requires-Dist: jsonschema
Requires-Dist: re
